{
    "name": "Symfony\\Component\\HttpFoundation\\Session\\Attribute\\NamespacedAttributeBag",
    "line": 20,
    "short_desc": "This class provides structured storage of session attributes using\na name spacing character in the key.",
    "long_desc": "",
    "hint": null,
    "tags": {
        "author": [
            [
                "Drak",
                "<drak@zikula.org>"
            ]
        ]
    },
    "namespace": "Symfony\\Component\\HttpFoundation\\Session\\Attribute",
    "file": "\/home\/cabox\/workspace\/core\/src\/Khan\/Component\/HttpFoundation\/Session\/Attribute\/NamespacedAttributeBag.php",
    "relative_file": null,
    "hash": "6081d633c9ed0a51090f107ad01cedfc7c94dc76",
    "parent": "Symfony\\Component\\HttpFoundation\\Session\\Attribute\\AttributeBag",
    "modifiers": 0,
    "is_trait": false,
    "is_interface": false,
    "aliases": [],
    "errors": [],
    "interfaces": [],
    "traits": [],
    "properties": [],
    "methods": {
        "__construct": {
            "name": "__construct",
            "line": 28,
            "short_desc": "",
            "long_desc": "",
            "hint": null,
            "hint_desc": null,
            "tags": [],
            "modifiers": 1,
            "is_by_ref": "",
            "exceptions": [],
            "errors": [],
            "parameters": {
                "storageKey": {
                    "name": "storageKey",
                    "line": 28,
                    "short_desc": "The key used to store attributes in the session",
                    "long_desc": null,
                    "hint": [
                        [
                            "string",
                            false
                        ]
                    ],
                    "tags": [],
                    "modifiers": "string",
                    "default": "'_sf2_attributes'",
                    "variadic": false,
                    "is_by_ref": false
                },
                "namespaceCharacter": {
                    "name": "namespaceCharacter",
                    "line": 28,
                    "short_desc": "Namespace character to use in keys",
                    "long_desc": null,
                    "hint": [
                        [
                            "string",
                            false
                        ]
                    ],
                    "tags": [],
                    "modifiers": "string",
                    "default": "'\/'",
                    "variadic": false,
                    "is_by_ref": false
                }
            }
        },
        "has": {
            "name": "has",
            "line": 37,
            "short_desc": "Checks if an attribute is defined.",
            "long_desc": "",
            "hint": [
                [
                    "bool",
                    false
                ]
            ],
            "hint_desc": "true if the attribute is defined, false otherwise",
            "tags": [],
            "modifiers": 1,
            "is_by_ref": "",
            "exceptions": [],
            "errors": [],
            "parameters": {
                "name": {
                    "name": "name",
                    "line": 37,
                    "short_desc": "The attribute name",
                    "long_desc": null,
                    "hint": [
                        [
                            "string",
                            false
                        ]
                    ],
                    "tags": [],
                    "modifiers": null,
                    "default": null,
                    "variadic": false,
                    "is_by_ref": false
                }
            }
        },
        "get": {
            "name": "get",
            "line": 53,
            "short_desc": "Returns an attribute.",
            "long_desc": "",
            "hint": [
                [
                    "mixed",
                    false
                ]
            ],
            "hint_desc": null,
            "tags": [],
            "modifiers": 1,
            "is_by_ref": "",
            "exceptions": [],
            "errors": [],
            "parameters": {
                "name": {
                    "name": "name",
                    "line": 53,
                    "short_desc": "The attribute name",
                    "long_desc": null,
                    "hint": [
                        [
                            "string",
                            false
                        ]
                    ],
                    "tags": [],
                    "modifiers": null,
                    "default": null,
                    "variadic": false,
                    "is_by_ref": false
                },
                "default": {
                    "name": "default",
                    "line": 53,
                    "short_desc": "The default value if not found",
                    "long_desc": null,
                    "hint": [
                        [
                            "mixed",
                            false
                        ]
                    ],
                    "tags": [],
                    "modifiers": null,
                    "default": "null",
                    "variadic": false,
                    "is_by_ref": false
                }
            }
        },
        "set": {
            "name": "set",
            "line": 69,
            "short_desc": "Sets an attribute.",
            "long_desc": "",
            "hint": null,
            "hint_desc": null,
            "tags": [],
            "modifiers": 1,
            "is_by_ref": "",
            "exceptions": [],
            "errors": [],
            "parameters": {
                "name": {
                    "name": "name",
                    "line": 69,
                    "short_desc": null,
                    "long_desc": null,
                    "hint": [
                        [
                            "string",
                            false
                        ]
                    ],
                    "tags": [],
                    "modifiers": null,
                    "default": null,
                    "variadic": false,
                    "is_by_ref": false
                },
                "value": {
                    "name": "value",
                    "line": 69,
                    "short_desc": null,
                    "long_desc": null,
                    "hint": [
                        [
                            "mixed",
                            false
                        ]
                    ],
                    "tags": [],
                    "modifiers": null,
                    "default": null,
                    "variadic": false,
                    "is_by_ref": false
                }
            }
        },
        "remove": {
            "name": "remove",
            "line": 79,
            "short_desc": "Removes an attribute.",
            "long_desc": "",
            "hint": [
                [
                    "mixed",
                    false
                ]
            ],
            "hint_desc": "The removed value or null when it does not exist",
            "tags": [],
            "modifiers": 1,
            "is_by_ref": "",
            "exceptions": [],
            "errors": [],
            "parameters": {
                "name": {
                    "name": "name",
                    "line": 79,
                    "short_desc": null,
                    "long_desc": null,
                    "hint": [
                        [
                            "string",
                            false
                        ]
                    ],
                    "tags": [],
                    "modifiers": null,
                    "default": null,
                    "variadic": false,
                    "is_by_ref": false
                }
            }
        },
        "resolveAttributePath": {
            "name": "resolveAttributePath",
            "line": 102,
            "short_desc": "Resolves a path in attributes property and returns it as a reference.",
            "long_desc": "This method allows structured namespacing of session attributes.",
            "hint": [
                [
                    "array",
                    false
                ]
            ],
            "hint_desc": "",
            "tags": [],
            "modifiers": 2,
            "is_by_ref": "1",
            "exceptions": [],
            "errors": [],
            "parameters": {
                "name": {
                    "name": "name",
                    "line": 102,
                    "short_desc": "Key name",
                    "long_desc": null,
                    "hint": [
                        [
                            "string",
                            false
                        ]
                    ],
                    "tags": [],
                    "modifiers": null,
                    "default": null,
                    "variadic": false,
                    "is_by_ref": false
                },
                "writeContext": {
                    "name": "writeContext",
                    "line": 102,
                    "short_desc": "Write context, default false",
                    "long_desc": null,
                    "hint": [
                        [
                            "bool",
                            false
                        ]
                    ],
                    "tags": [],
                    "modifiers": null,
                    "default": "false",
                    "variadic": false,
                    "is_by_ref": false
                }
            }
        },
        "resolveKey": {
            "name": "resolveKey",
            "line": 145,
            "short_desc": "Resolves the key from the name.",
            "long_desc": "This is the last part in a dot separated string.",
            "hint": [
                [
                    "string",
                    false
                ]
            ],
            "hint_desc": "",
            "tags": [],
            "modifiers": 2,
            "is_by_ref": "",
            "exceptions": [],
            "errors": [],
            "parameters": {
                "name": {
                    "name": "name",
                    "line": 145,
                    "short_desc": "",
                    "long_desc": null,
                    "hint": [
                        [
                            "string",
                            false
                        ]
                    ],
                    "tags": [],
                    "modifiers": null,
                    "default": null,
                    "variadic": false,
                    "is_by_ref": false
                }
            }
        }
    },
    "constants": []
}